<?xml version="1.0"?>
<property-set xmlns="http://mcc.lip6.fr/">
  <property>
    <id>BridgeAndVehicles-COL-V20P10N50-CTLFireabilitySimple-0</id>
    <description>Automatically generated</description>
    <formula>
      <all-paths>
        <finally>
          <is-fireable>
            <transition>autorisation_B_2_1</transition>
            <transition>autorisation_B_2_2</transition>
            <transition>autorisation_B_2_3</transition>
            <transition>autorisation_B_2_4</transition>
            <transition>autorisation_B_2_5</transition>
            <transition>autorisation_B_2_6</transition>
            <transition>autorisation_B_2_7</transition>
            <transition>autorisation_B_2_8</transition>
            <transition>autorisation_B_2_9</transition>
            <transition>autorisation_B_2_10</transition>
            <transition>autorisation_B_2_11</transition>
            <transition>autorisation_B_2_12</transition>
            <transition>autorisation_B_2_13</transition>
            <transition>autorisation_B_2_14</transition>
            <transition>autorisation_B_2_15</transition>
            <transition>autorisation_B_2_16</transition>
            <transition>autorisation_B_2_17</transition>
            <transition>autorisation_B_2_18</transition>
            <transition>autorisation_B_2_19</transition>
            <transition>autorisation_B_2_20</transition>
          </is-fireable>
        </finally>
      </all-paths>
    </formula>
  </property>
  <property>
    <id>BridgeAndVehicles-COL-V20P10N50-CTLFireabilitySimple-1</id>
    <description>Automatically generated</description>
    <formula>
      <exists-path>
        <until>
          <before>
            <is-fireable>
              <transition>enregistrement_A_0</transition>
              <transition>enregistrement_A_1</transition>
              <transition>enregistrement_A_2</transition>
              <transition>enregistrement_A_3</transition>
              <transition>enregistrement_A_4</transition>
              <transition>enregistrement_A_5</transition>
              <transition>enregistrement_A_6</transition>
              <transition>enregistrement_A_7</transition>
              <transition>enregistrement_A_8</transition>
              <transition>enregistrement_A_9</transition>
              <transition>enregistrement_A_10</transition>
              <transition>enregistrement_A_11</transition>
              <transition>enregistrement_A_12</transition>
              <transition>enregistrement_A_13</transition>
              <transition>enregistrement_A_14</transition>
              <transition>enregistrement_A_15</transition>
              <transition>enregistrement_A_16</transition>
              <transition>enregistrement_A_17</transition>
              <transition>enregistrement_A_18</transition>
              <transition>enregistrement_A_19</transition>
              <transition>enregistrement_A_20</transition>
            </is-fireable>
          </before>
          <reach>
            <is-fireable>
              <transition>altern_cpt_50_1</transition>
              <transition>altern_cpt_50_2</transition>
            </is-fireable>
          </reach>
        </until>
      </exists-path>
    </formula>
  </property>
  <property>
    <id>BridgeAndVehicles-COL-V20P10N50-CTLFireabilitySimple-2</id>
    <description>Automatically generated</description>
    <formula>
      <exists-path>
        <globally>
          <is-fireable>
            <transition>enregistrement_B_0</transition>
            <transition>enregistrement_B_1</transition>
            <transition>enregistrement_B_2</transition>
            <transition>enregistrement_B_3</transition>
            <transition>enregistrement_B_4</transition>
            <transition>enregistrement_B_5</transition>
            <transition>enregistrement_B_6</transition>
            <transition>enregistrement_B_7</transition>
            <transition>enregistrement_B_8</transition>
            <transition>enregistrement_B_9</transition>
            <transition>enregistrement_B_10</transition>
            <transition>enregistrement_B_11</transition>
            <transition>enregistrement_B_12</transition>
            <transition>enregistrement_B_13</transition>
            <transition>enregistrement_B_14</transition>
            <transition>enregistrement_B_15</transition>
            <transition>enregistrement_B_16</transition>
            <transition>enregistrement_B_17</transition>
            <transition>enregistrement_B_18</transition>
            <transition>enregistrement_B_19</transition>
            <transition>enregistrement_B_20</transition>
          </is-fireable>
        </globally>
      </exists-path>
    </formula>
  </property>
  <property>
    <id>BridgeAndVehicles-COL-V20P10N50-CTLFireabilitySimple-3</id>
    <description>Automatically generated</description>
    <formula>
      <all-paths>
        <finally>
          <is-fireable>
            <transition>autorisation_A_1_1</transition>
            <transition>autorisation_A_2_1</transition>
            <transition>autorisation_A_3_1</transition>
            <transition>autorisation_A_4_1</transition>
            <transition>autorisation_A_5_1</transition>
            <transition>autorisation_A_6_1</transition>
            <transition>autorisation_A_7_1</transition>
            <transition>autorisation_A_8_1</transition>
            <transition>autorisation_A_9_1</transition>
            <transition>autorisation_A_10_1</transition>
            <transition>autorisation_A_11_1</transition>
            <transition>autorisation_A_12_1</transition>
            <transition>autorisation_A_13_1</transition>
            <transition>autorisation_A_14_1</transition>
            <transition>autorisation_A_15_1</transition>
            <transition>autorisation_A_16_1</transition>
            <transition>autorisation_A_17_1</transition>
            <transition>autorisation_A_18_1</transition>
            <transition>autorisation_A_19_1</transition>
            <transition>autorisation_A_20_1</transition>
          </is-fireable>
        </finally>
      </all-paths>
    </formula>
  </property>
  <property>
    <id>BridgeAndVehicles-COL-V20P10N50-CTLFireabilitySimple-4</id>
    <description>Automatically generated</description>
    <formula>
      <all-paths>
        <globally>
          <is-fireable>
            <transition>enregistrement_A_0</transition>
            <transition>enregistrement_A_1</transition>
            <transition>enregistrement_A_2</transition>
            <transition>enregistrement_A_3</transition>
            <transition>enregistrement_A_4</transition>
            <transition>enregistrement_A_5</transition>
            <transition>enregistrement_A_6</transition>
            <transition>enregistrement_A_7</transition>
            <transition>enregistrement_A_8</transition>
            <transition>enregistrement_A_9</transition>
            <transition>enregistrement_A_10</transition>
            <transition>enregistrement_A_11</transition>
            <transition>enregistrement_A_12</transition>
            <transition>enregistrement_A_13</transition>
            <transition>enregistrement_A_14</transition>
            <transition>enregistrement_A_15</transition>
            <transition>enregistrement_A_16</transition>
            <transition>enregistrement_A_17</transition>
            <transition>enregistrement_A_18</transition>
            <transition>enregistrement_A_19</transition>
            <transition>enregistrement_A_20</transition>
          </is-fireable>
        </globally>
      </all-paths>
    </formula>
  </property>
  <property>
    <id>BridgeAndVehicles-COL-V20P10N50-CTLFireabilitySimple-5</id>
    <description>Automatically generated</description>
    <formula>
      <all-paths>
        <globally>
          <is-fireable>
            <transition>enregistrement_A_0</transition>
            <transition>enregistrement_A_1</transition>
            <transition>enregistrement_A_2</transition>
            <transition>enregistrement_A_3</transition>
            <transition>enregistrement_A_4</transition>
            <transition>enregistrement_A_5</transition>
            <transition>enregistrement_A_6</transition>
            <transition>enregistrement_A_7</transition>
            <transition>enregistrement_A_8</transition>
            <transition>enregistrement_A_9</transition>
            <transition>enregistrement_A_10</transition>
            <transition>enregistrement_A_11</transition>
            <transition>enregistrement_A_12</transition>
            <transition>enregistrement_A_13</transition>
            <transition>enregistrement_A_14</transition>
            <transition>enregistrement_A_15</transition>
            <transition>enregistrement_A_16</transition>
            <transition>enregistrement_A_17</transition>
            <transition>enregistrement_A_18</transition>
            <transition>enregistrement_A_19</transition>
            <transition>enregistrement_A_20</transition>
          </is-fireable>
        </globally>
      </all-paths>
    </formula>
  </property>
  <property>
    <id>BridgeAndVehicles-COL-V20P10N50-CTLFireabilitySimple-6</id>
    <description>Automatically generated</description>
    <formula>
      <all-paths>
        <globally>
          <is-fireable>
            <transition>enregistrement_A_0</transition>
            <transition>enregistrement_A_1</transition>
            <transition>enregistrement_A_2</transition>
            <transition>enregistrement_A_3</transition>
            <transition>enregistrement_A_4</transition>
            <transition>enregistrement_A_5</transition>
            <transition>enregistrement_A_6</transition>
            <transition>enregistrement_A_7</transition>
            <transition>enregistrement_A_8</transition>
            <transition>enregistrement_A_9</transition>
            <transition>enregistrement_A_10</transition>
            <transition>enregistrement_A_11</transition>
            <transition>enregistrement_A_12</transition>
            <transition>enregistrement_A_13</transition>
            <transition>enregistrement_A_14</transition>
            <transition>enregistrement_A_15</transition>
            <transition>enregistrement_A_16</transition>
            <transition>enregistrement_A_17</transition>
            <transition>enregistrement_A_18</transition>
            <transition>enregistrement_A_19</transition>
            <transition>enregistrement_A_20</transition>
          </is-fireable>
        </globally>
      </all-paths>
    </formula>
  </property>
  <property>
    <id>BridgeAndVehicles-COL-V20P10N50-CTLFireabilitySimple-7</id>
    <description>Automatically generated</description>
    <formula>
      <exists-path>
        <globally>
          <is-fireable>
            <transition>enregistrement_A_0</transition>
            <transition>enregistrement_A_1</transition>
            <transition>enregistrement_A_2</transition>
            <transition>enregistrement_A_3</transition>
            <transition>enregistrement_A_4</transition>
            <transition>enregistrement_A_5</transition>
            <transition>enregistrement_A_6</transition>
            <transition>enregistrement_A_7</transition>
            <transition>enregistrement_A_8</transition>
            <transition>enregistrement_A_9</transition>
            <transition>enregistrement_A_10</transition>
            <transition>enregistrement_A_11</transition>
            <transition>enregistrement_A_12</transition>
            <transition>enregistrement_A_13</transition>
            <transition>enregistrement_A_14</transition>
            <transition>enregistrement_A_15</transition>
            <transition>enregistrement_A_16</transition>
            <transition>enregistrement_A_17</transition>
            <transition>enregistrement_A_18</transition>
            <transition>enregistrement_A_19</transition>
            <transition>enregistrement_A_20</transition>
          </is-fireable>
        </globally>
      </exists-path>
    </formula>
  </property>
  <property>
    <id>BridgeAndVehicles-COL-V20P10N50-CTLFireabilitySimple-8</id>
    <description>Automatically generated</description>
    <formula>
      <all-paths>
        <until>
          <before>
            <is-fireable>
              <transition>enregistrement_A_0</transition>
              <transition>enregistrement_A_1</transition>
              <transition>enregistrement_A_2</transition>
              <transition>enregistrement_A_3</transition>
              <transition>enregistrement_A_4</transition>
              <transition>enregistrement_A_5</transition>
              <transition>enregistrement_A_6</transition>
              <transition>enregistrement_A_7</transition>
              <transition>enregistrement_A_8</transition>
              <transition>enregistrement_A_9</transition>
              <transition>enregistrement_A_10</transition>
              <transition>enregistrement_A_11</transition>
              <transition>enregistrement_A_12</transition>
              <transition>enregistrement_A_13</transition>
              <transition>enregistrement_A_14</transition>
              <transition>enregistrement_A_15</transition>
              <transition>enregistrement_A_16</transition>
              <transition>enregistrement_A_17</transition>
              <transition>enregistrement_A_18</transition>
              <transition>enregistrement_A_19</transition>
              <transition>enregistrement_A_20</transition>
            </is-fireable>
          </before>
          <reach>
            <is-fireable>
              <transition>autorisation_A_1_1</transition>
              <transition>autorisation_A_2_1</transition>
              <transition>autorisation_A_3_1</transition>
              <transition>autorisation_A_4_1</transition>
              <transition>autorisation_A_5_1</transition>
              <transition>autorisation_A_6_1</transition>
              <transition>autorisation_A_7_1</transition>
              <transition>autorisation_A_8_1</transition>
              <transition>autorisation_A_9_1</transition>
              <transition>autorisation_A_10_1</transition>
              <transition>autorisation_A_11_1</transition>
              <transition>autorisation_A_12_1</transition>
              <transition>autorisation_A_13_1</transition>
              <transition>autorisation_A_14_1</transition>
              <transition>autorisation_A_15_1</transition>
              <transition>autorisation_A_16_1</transition>
              <transition>autorisation_A_17_1</transition>
              <transition>autorisation_A_18_1</transition>
              <transition>autorisation_A_19_1</transition>
              <transition>autorisation_A_20_1</transition>
            </is-fireable>
          </reach>
        </until>
      </all-paths>
    </formula>
  </property>
  <property>
    <id>BridgeAndVehicles-COL-V20P10N50-CTLFireabilitySimple-9</id>
    <description>Automatically generated</description>
    <formula>
      <all-paths>
        <finally>
          <is-fireable>
            <transition>altern_cpt_50_1</transition>
            <transition>altern_cpt_50_2</transition>
          </is-fireable>
        </finally>
      </all-paths>
    </formula>
  </property>
  <property>
    <id>BridgeAndVehicles-COL-V20P10N50-CTLFireabilitySimple-10</id>
    <description>Automatically generated</description>
    <formula>
      <all-paths>
        <until>
          <before>
            <is-fireable>
              <transition>enregistrement_A_0</transition>
              <transition>enregistrement_A_1</transition>
              <transition>enregistrement_A_2</transition>
              <transition>enregistrement_A_3</transition>
              <transition>enregistrement_A_4</transition>
              <transition>enregistrement_A_5</transition>
              <transition>enregistrement_A_6</transition>
              <transition>enregistrement_A_7</transition>
              <transition>enregistrement_A_8</transition>
              <transition>enregistrement_A_9</transition>
              <transition>enregistrement_A_10</transition>
              <transition>enregistrement_A_11</transition>
              <transition>enregistrement_A_12</transition>
              <transition>enregistrement_A_13</transition>
              <transition>enregistrement_A_14</transition>
              <transition>enregistrement_A_15</transition>
              <transition>enregistrement_A_16</transition>
              <transition>enregistrement_A_17</transition>
              <transition>enregistrement_A_18</transition>
              <transition>enregistrement_A_19</transition>
              <transition>enregistrement_A_20</transition>
            </is-fireable>
          </before>
          <reach>
            <is-fireable>
              <transition>autorisation_A_1_1</transition>
              <transition>autorisation_A_2_1</transition>
              <transition>autorisation_A_3_1</transition>
              <transition>autorisation_A_4_1</transition>
              <transition>autorisation_A_5_1</transition>
              <transition>autorisation_A_6_1</transition>
              <transition>autorisation_A_7_1</transition>
              <transition>autorisation_A_8_1</transition>
              <transition>autorisation_A_9_1</transition>
              <transition>autorisation_A_10_1</transition>
              <transition>autorisation_A_11_1</transition>
              <transition>autorisation_A_12_1</transition>
              <transition>autorisation_A_13_1</transition>
              <transition>autorisation_A_14_1</transition>
              <transition>autorisation_A_15_1</transition>
              <transition>autorisation_A_16_1</transition>
              <transition>autorisation_A_17_1</transition>
              <transition>autorisation_A_18_1</transition>
              <transition>autorisation_A_19_1</transition>
              <transition>autorisation_A_20_1</transition>
            </is-fireable>
          </reach>
        </until>
      </all-paths>
    </formula>
  </property>
  <property>
    <id>BridgeAndVehicles-COL-V20P10N50-CTLFireabilitySimple-11</id>
    <description>Automatically generated</description>
    <formula>
      <exists-path>
        <globally>
          <is-fireable>
            <transition>enregistrement_A_0</transition>
            <transition>enregistrement_A_1</transition>
            <transition>enregistrement_A_2</transition>
            <transition>enregistrement_A_3</transition>
            <transition>enregistrement_A_4</transition>
            <transition>enregistrement_A_5</transition>
            <transition>enregistrement_A_6</transition>
            <transition>enregistrement_A_7</transition>
            <transition>enregistrement_A_8</transition>
            <transition>enregistrement_A_9</transition>
            <transition>enregistrement_A_10</transition>
            <transition>enregistrement_A_11</transition>
            <transition>enregistrement_A_12</transition>
            <transition>enregistrement_A_13</transition>
            <transition>enregistrement_A_14</transition>
            <transition>enregistrement_A_15</transition>
            <transition>enregistrement_A_16</transition>
            <transition>enregistrement_A_17</transition>
            <transition>enregistrement_A_18</transition>
            <transition>enregistrement_A_19</transition>
            <transition>enregistrement_A_20</transition>
          </is-fireable>
        </globally>
      </exists-path>
    </formula>
  </property>
  <property>
    <id>BridgeAndVehicles-COL-V20P10N50-CTLFireabilitySimple-12</id>
    <description>Automatically generated</description>
    <formula>
      <all-paths>
        <until>
          <before>
            <is-fireable>
              <transition>enregistrement_A_0</transition>
              <transition>enregistrement_A_1</transition>
              <transition>enregistrement_A_2</transition>
              <transition>enregistrement_A_3</transition>
              <transition>enregistrement_A_4</transition>
              <transition>enregistrement_A_5</transition>
              <transition>enregistrement_A_6</transition>
              <transition>enregistrement_A_7</transition>
              <transition>enregistrement_A_8</transition>
              <transition>enregistrement_A_9</transition>
              <transition>enregistrement_A_10</transition>
              <transition>enregistrement_A_11</transition>
              <transition>enregistrement_A_12</transition>
              <transition>enregistrement_A_13</transition>
              <transition>enregistrement_A_14</transition>
              <transition>enregistrement_A_15</transition>
              <transition>enregistrement_A_16</transition>
              <transition>enregistrement_A_17</transition>
              <transition>enregistrement_A_18</transition>
              <transition>enregistrement_A_19</transition>
              <transition>enregistrement_A_20</transition>
            </is-fireable>
          </before>
          <reach>
            <is-fireable>
              <transition>autorisation_A_1_1</transition>
              <transition>autorisation_A_2_1</transition>
              <transition>autorisation_A_3_1</transition>
              <transition>autorisation_A_4_1</transition>
              <transition>autorisation_A_5_1</transition>
              <transition>autorisation_A_6_1</transition>
              <transition>autorisation_A_7_1</transition>
              <transition>autorisation_A_8_1</transition>
              <transition>autorisation_A_9_1</transition>
              <transition>autorisation_A_10_1</transition>
              <transition>autorisation_A_11_1</transition>
              <transition>autorisation_A_12_1</transition>
              <transition>autorisation_A_13_1</transition>
              <transition>autorisation_A_14_1</transition>
              <transition>autorisation_A_15_1</transition>
              <transition>autorisation_A_16_1</transition>
              <transition>autorisation_A_17_1</transition>
              <transition>autorisation_A_18_1</transition>
              <transition>autorisation_A_19_1</transition>
              <transition>autorisation_A_20_1</transition>
            </is-fireable>
          </reach>
        </until>
      </all-paths>
    </formula>
  </property>
  <property>
    <id>BridgeAndVehicles-COL-V20P10N50-CTLFireabilitySimple-13</id>
    <description>Automatically generated</description>
    <formula>
      <all-paths>
        <finally>
          <is-fireable>
            <transition>autorisation_A_1_1</transition>
            <transition>autorisation_A_2_1</transition>
            <transition>autorisation_A_3_1</transition>
            <transition>autorisation_A_4_1</transition>
            <transition>autorisation_A_5_1</transition>
            <transition>autorisation_A_6_1</transition>
            <transition>autorisation_A_7_1</transition>
            <transition>autorisation_A_8_1</transition>
            <transition>autorisation_A_9_1</transition>
            <transition>autorisation_A_10_1</transition>
            <transition>autorisation_A_11_1</transition>
            <transition>autorisation_A_12_1</transition>
            <transition>autorisation_A_13_1</transition>
            <transition>autorisation_A_14_1</transition>
            <transition>autorisation_A_15_1</transition>
            <transition>autorisation_A_16_1</transition>
            <transition>autorisation_A_17_1</transition>
            <transition>autorisation_A_18_1</transition>
            <transition>autorisation_A_19_1</transition>
            <transition>autorisation_A_20_1</transition>
          </is-fireable>
        </finally>
      </all-paths>
    </formula>
  </property>
  <property>
    <id>BridgeAndVehicles-COL-V20P10N50-CTLFireabilitySimple-14</id>
    <description>Automatically generated</description>
    <formula>
      <exists-path>
        <globally>
          <is-fireable>
            <transition>enregistrement_B_0</transition>
            <transition>enregistrement_B_1</transition>
            <transition>enregistrement_B_2</transition>
            <transition>enregistrement_B_3</transition>
            <transition>enregistrement_B_4</transition>
            <transition>enregistrement_B_5</transition>
            <transition>enregistrement_B_6</transition>
            <transition>enregistrement_B_7</transition>
            <transition>enregistrement_B_8</transition>
            <transition>enregistrement_B_9</transition>
            <transition>enregistrement_B_10</transition>
            <transition>enregistrement_B_11</transition>
            <transition>enregistrement_B_12</transition>
            <transition>enregistrement_B_13</transition>
            <transition>enregistrement_B_14</transition>
            <transition>enregistrement_B_15</transition>
            <transition>enregistrement_B_16</transition>
            <transition>enregistrement_B_17</transition>
            <transition>enregistrement_B_18</transition>
            <transition>enregistrement_B_19</transition>
            <transition>enregistrement_B_20</transition>
          </is-fireable>
        </globally>
      </exists-path>
    </formula>
  </property>
  <property>
    <id>BridgeAndVehicles-COL-V20P10N50-CTLFireabilitySimple-15</id>
    <description>Automatically generated</description>
    <formula>
      <exists-path>
        <globally>
          <is-fireable>
            <transition>decision_0_1</transition>
            <transition>decision_1_1</transition>
            <transition>decision_2_1</transition>
            <transition>decision_3_1</transition>
            <transition>decision_4_1</transition>
            <transition>decision_5_1</transition>
            <transition>decision_6_1</transition>
            <transition>decision_7_1</transition>
            <transition>decision_8_1</transition>
            <transition>decision_9_1</transition>
            <transition>decision_10_1</transition>
            <transition>decision_11_1</transition>
            <transition>decision_12_1</transition>
            <transition>decision_13_1</transition>
            <transition>decision_14_1</transition>
            <transition>decision_15_1</transition>
            <transition>decision_16_1</transition>
            <transition>decision_17_1</transition>
            <transition>decision_18_1</transition>
            <transition>decision_19_1</transition>
            <transition>decision_20_1</transition>
            <transition>decision_21_1</transition>
            <transition>decision_22_1</transition>
            <transition>decision_23_1</transition>
            <transition>decision_24_1</transition>
            <transition>decision_25_1</transition>
            <transition>decision_26_1</transition>
            <transition>decision_27_1</transition>
            <transition>decision_28_1</transition>
            <transition>decision_29_1</transition>
            <transition>decision_30_1</transition>
            <transition>decision_31_1</transition>
            <transition>decision_32_1</transition>
            <transition>decision_33_1</transition>
            <transition>decision_34_1</transition>
            <transition>decision_35_1</transition>
            <transition>decision_36_1</transition>
            <transition>decision_37_1</transition>
            <transition>decision_38_1</transition>
            <transition>decision_39_1</transition>
            <transition>decision_40_1</transition>
            <transition>decision_41_1</transition>
            <transition>decision_42_1</transition>
            <transition>decision_43_1</transition>
            <transition>decision_44_1</transition>
            <transition>decision_45_1</transition>
            <transition>decision_46_1</transition>
            <transition>decision_47_1</transition>
            <transition>decision_48_1</transition>
            <transition>decision_49_1</transition>
            <transition>decision_0_2</transition>
            <transition>decision_1_2</transition>
            <transition>decision_2_2</transition>
            <transition>decision_3_2</transition>
            <transition>decision_4_2</transition>
            <transition>decision_5_2</transition>
            <transition>decision_6_2</transition>
            <transition>decision_7_2</transition>
            <transition>decision_8_2</transition>
            <transition>decision_9_2</transition>
            <transition>decision_10_2</transition>
            <transition>decision_11_2</transition>
            <transition>decision_12_2</transition>
            <transition>decision_13_2</transition>
            <transition>decision_14_2</transition>
            <transition>decision_15_2</transition>
            <transition>decision_16_2</transition>
            <transition>decision_17_2</transition>
            <transition>decision_18_2</transition>
            <transition>decision_19_2</transition>
            <transition>decision_20_2</transition>
            <transition>decision_21_2</transition>
            <transition>decision_22_2</transition>
            <transition>decision_23_2</transition>
            <transition>decision_24_2</transition>
            <transition>decision_25_2</transition>
            <transition>decision_26_2</transition>
            <transition>decision_27_2</transition>
            <transition>decision_28_2</transition>
            <transition>decision_29_2</transition>
            <transition>decision_30_2</transition>
            <transition>decision_31_2</transition>
            <transition>decision_32_2</transition>
            <transition>decision_33_2</transition>
            <transition>decision_34_2</transition>
            <transition>decision_35_2</transition>
            <transition>decision_36_2</transition>
            <transition>decision_37_2</transition>
            <transition>decision_38_2</transition>
            <transition>decision_39_2</transition>
            <transition>decision_40_2</transition>
            <transition>decision_41_2</transition>
            <transition>decision_42_2</transition>
            <transition>decision_43_2</transition>
            <transition>decision_44_2</transition>
            <transition>decision_45_2</transition>
            <transition>decision_46_2</transition>
            <transition>decision_47_2</transition>
            <transition>decision_48_2</transition>
            <transition>decision_49_2</transition>
          </is-fireable>
        </globally>
      </exists-path>
    </formula>
  </property>
</property-set>
