<?xml version="1.0"?>
<property-set xmlns="http://mcc.lip6.fr/">
  <property>
    <id>Railroad-PT-010-ReachabilityFireability-0</id>
    <description>Automatically generated</description>
    <formula>
      <exists-path>
        <finally>
          <conjunction>
            <negation>
              <conjunction>
                <conjunction>
                  <is-fireable>
                    <transition>tr_T33_32</transition>
                  </is-fireable>
                  <is-fireable>
                    <transition>tr_T33_70</transition>
                  </is-fireable>
                </conjunction>
                <is-fireable>
                  <transition>tr_T15_1</transition>
                </is-fireable>
              </conjunction>
            </negation>
            <conjunction>
              <conjunction>
                <negation>
                  <is-fireable>
                    <transition>tr_T33_81</transition>
                  </is-fireable>
                </negation>
                <conjunction>
                  <is-fireable>
                    <transition>tr_T33_113</transition>
                  </is-fireable>
                  <is-fireable>
                    <transition>tr_T37_10</transition>
                  </is-fireable>
                </conjunction>
              </conjunction>
              <is-fireable>
                <transition>tr_T33_53</transition>
              </is-fireable>
            </conjunction>
          </conjunction>
        </finally>
      </exists-path>
    </formula>
  </property>
  <property>
    <id>Railroad-PT-010-ReachabilityFireability-1</id>
    <description>Automatically generated</description>
    <formula>
      <exists-path>
        <finally>
          <disjunction>
            <negation>
              <negation>
                <conjunction>
                  <is-fireable>
                    <transition>tr_T38_1</transition>
                  </is-fireable>
                  <is-fireable>
                    <transition>tr_T37_10</transition>
                  </is-fireable>
                </conjunction>
              </negation>
            </negation>
            <disjunction>
              <conjunction>
                <conjunction>
                  <is-fireable>
                    <transition>tr_T33_109</transition>
                  </is-fireable>
                  <is-fireable>
                    <transition>tr_T33_113</transition>
                  </is-fireable>
                </conjunction>
                <disjunction>
                  <is-fireable>
                    <transition>tr_T33_28</transition>
                  </is-fireable>
                  <is-fireable>
                    <transition>tr_T33_50</transition>
                  </is-fireable>
                </disjunction>
              </conjunction>
              <conjunction>
                <negation>
                  <is-fireable>
                    <transition>tr_T25_1</transition>
                  </is-fireable>
                </negation>
                <is-fireable>
                  <transition>tr_T33_109</transition>
                </is-fireable>
              </conjunction>
            </disjunction>
          </disjunction>
        </finally>
      </exists-path>
    </formula>
  </property>
  <property>
    <id>Railroad-PT-010-ReachabilityFireability-2</id>
    <description>Automatically generated</description>
    <formula>
      <exists-path>
        <finally>
          <is-fireable>
            <transition>tr_T33_89</transition>
          </is-fireable>
        </finally>
      </exists-path>
    </formula>
  </property>
  <property>
    <id>Railroad-PT-010-ReachabilityFireability-3</id>
    <description>Automatically generated</description>
    <formula>
      <exists-path>
        <finally>
          <is-fireable>
            <transition>tr_T33_51</transition>
          </is-fireable>
        </finally>
      </exists-path>
    </formula>
  </property>
  <property>
    <id>Railroad-PT-010-ReachabilityFireability-4</id>
    <description>Automatically generated</description>
    <formula>
      <exists-path>
        <finally>
          <conjunction>
            <disjunction>
              <conjunction>
                <negation>
                  <is-fireable>
                    <transition>tr_T33_26</transition>
                  </is-fireable>
                </negation>
                <is-fireable>
                  <transition>tr_T17_1</transition>
                </is-fireable>
              </conjunction>
              <is-fireable>
                <transition>tr_T5_1</transition>
              </is-fireable>
            </disjunction>
            <conjunction>
              <is-fireable>
                <transition>tr_T33_99</transition>
              </is-fireable>
              <is-fireable>
                <transition>tr_T33_77</transition>
              </is-fireable>
            </conjunction>
          </conjunction>
        </finally>
      </exists-path>
    </formula>
  </property>
  <property>
    <id>Railroad-PT-010-ReachabilityFireability-5</id>
    <description>Automatically generated</description>
    <formula>
      <exists-path>
        <finally>
          <conjunction>
            <conjunction>
              <is-fireable>
                <transition>tr_T33_70</transition>
              </is-fireable>
              <negation>
                <negation>
                  <is-fireable>
                    <transition>tr_T33_40</transition>
                  </is-fireable>
                </negation>
              </negation>
            </conjunction>
            <is-fireable>
              <transition>tr_T33_38</transition>
            </is-fireable>
          </conjunction>
        </finally>
      </exists-path>
    </formula>
  </property>
  <property>
    <id>Railroad-PT-010-ReachabilityFireability-6</id>
    <description>Automatically generated</description>
    <formula>
      <exists-path>
        <finally>
          <is-fireable>
            <transition>tr_T33_114</transition>
          </is-fireable>
        </finally>
      </exists-path>
    </formula>
  </property>
  <property>
    <id>Railroad-PT-010-ReachabilityFireability-7</id>
    <description>Automatically generated</description>
    <formula>
      <all-paths>
        <globally>
          <negation>
            <is-fireable>
              <transition>tr_T33_106</transition>
            </is-fireable>
          </negation>
        </globally>
      </all-paths>
    </formula>
  </property>
  <property>
    <id>Railroad-PT-010-ReachabilityFireability-8</id>
    <description>Automatically generated</description>
    <formula>
      <exists-path>
        <finally>
          <conjunction>
            <is-fireable>
              <transition>tr_T10_1</transition>
            </is-fireable>
            <conjunction>
              <disjunction>
                <negation>
                  <is-fireable>
                    <transition>tr_T33_97</transition>
                  </is-fireable>
                </negation>
                <negation>
                  <is-fireable>
                    <transition>tr_T15_1</transition>
                  </is-fireable>
                </negation>
              </disjunction>
              <negation>
                <disjunction>
                  <is-fireable>
                    <transition>tr_T33_77</transition>
                  </is-fireable>
                  <is-fireable>
                    <transition>tr_T33_77</transition>
                  </is-fireable>
                </disjunction>
              </negation>
            </conjunction>
          </conjunction>
        </finally>
      </exists-path>
    </formula>
  </property>
  <property>
    <id>Railroad-PT-010-ReachabilityFireability-9</id>
    <description>Automatically generated</description>
    <formula>
      <exists-path>
        <finally>
          <conjunction>
            <negation>
              <disjunction>
                <negation>
                  <is-fireable>
                    <transition>tr_T13_1</transition>
                  </is-fireable>
                </negation>
                <disjunction>
                  <is-fireable>
                    <transition>tr_T33_62</transition>
                  </is-fireable>
                  <is-fireable>
                    <transition>tr_T37_10</transition>
                  </is-fireable>
                </disjunction>
              </disjunction>
            </negation>
            <conjunction>
              <is-fireable>
                <transition>tr_T33_56</transition>
              </is-fireable>
              <negation>
                <is-fireable>
                  <transition>tr_T33_111</transition>
                </is-fireable>
              </negation>
            </conjunction>
          </conjunction>
        </finally>
      </exists-path>
    </formula>
  </property>
  <property>
    <id>Railroad-PT-010-ReachabilityFireability-10</id>
    <description>Automatically generated</description>
    <formula>
      <exists-path>
        <finally>
          <is-fireable>
            <transition>tr_T33_85</transition>
          </is-fireable>
        </finally>
      </exists-path>
    </formula>
  </property>
  <property>
    <id>Railroad-PT-010-ReachabilityFireability-11</id>
    <description>Automatically generated</description>
    <formula>
      <exists-path>
        <finally>
          <is-fireable>
            <transition>tr_T33_46</transition>
          </is-fireable>
        </finally>
      </exists-path>
    </formula>
  </property>
  <property>
    <id>Railroad-PT-010-ReachabilityFireability-12</id>
    <description>Automatically generated</description>
    <formula>
      <all-paths>
        <globally>
          <negation>
            <conjunction>
              <negation>
                <disjunction>
                  <is-fireable>
                    <transition>tr_T33_28</transition>
                  </is-fireable>
                  <is-fireable>
                    <transition>tr_T1_1</transition>
                  </is-fireable>
                </disjunction>
              </negation>
              <is-fireable>
                <transition>tr_T33_73</transition>
              </is-fireable>
            </conjunction>
          </negation>
        </globally>
      </all-paths>
    </formula>
  </property>
  <property>
    <id>Railroad-PT-010-ReachabilityFireability-13</id>
    <description>Automatically generated</description>
    <formula>
      <exists-path>
        <finally>
          <is-fireable>
            <transition>tr_T33_52</transition>
          </is-fireable>
        </finally>
      </exists-path>
    </formula>
  </property>
  <property>
    <id>Railroad-PT-010-ReachabilityFireability-14</id>
    <description>Automatically generated</description>
    <formula>
      <exists-path>
        <finally>
          <conjunction>
            <disjunction>
              <negation>
                <is-fireable>
                  <transition>tr_T33_62</transition>
                </is-fireable>
              </negation>
              <disjunction>
                <disjunction>
                  <is-fireable>
                    <transition>tr_T14_21</transition>
                  </is-fireable>
                  <is-fireable>
                    <transition>tr_T32_1</transition>
                  </is-fireable>
                </disjunction>
                <is-fireable>
                  <transition>tr_T37_10</transition>
                </is-fireable>
              </disjunction>
            </disjunction>
            <conjunction>
              <is-fireable>
                <transition>tr_T33_78</transition>
              </is-fireable>
              <disjunction>
                <negation>
                  <is-fireable>
                    <transition>tr_T33_76</transition>
                  </is-fireable>
                </negation>
                <conjunction>
                  <is-fireable>
                    <transition>tr_T14_22</transition>
                  </is-fireable>
                  <is-fireable>
                    <transition>tr_T18_1</transition>
                  </is-fireable>
                </conjunction>
              </disjunction>
            </conjunction>
          </conjunction>
        </finally>
      </exists-path>
    </formula>
  </property>
  <property>
    <id>Railroad-PT-010-ReachabilityFireability-15</id>
    <description>Automatically generated</description>
    <formula>
      <exists-path>
        <finally>
          <conjunction>
            <is-fireable>
              <transition>tr_T33_117</transition>
            </is-fireable>
            <is-fireable>
              <transition>tr_T14_20</transition>
            </is-fireable>
          </conjunction>
        </finally>
      </exists-path>
    </formula>
  </property>
</property-set>
