<?xml version="1.0"?>
<property-set xmlns="http://mcc.lip6.fr/">
  <property>
    <id>PhaseVariation-PT-D10CS010-LTLCardinality-0</id>
    <description>Automatically generated</description>
    <formula>
      <all-paths>
        <next>
          <next>
            <finally>
              <integer-le>
                <integer-constant>2</integer-constant>
                <tokens-count>
                  <place>cell___8_5__B_</place>
                </tokens-count>
              </integer-le>
            </finally>
          </next>
        </next>
      </all-paths>
    </formula>
  </property>
  <property>
    <id>PhaseVariation-PT-D10CS010-LTLCardinality-1</id>
    <description>Automatically generated</description>
    <formula>
      <all-paths>
        <next>
          <next>
            <globally>
              <globally>
                <integer-le>
                  <integer-constant>3</integer-constant>
                  <tokens-count>
                    <place>cell___6_7__A_</place>
                  </tokens-count>
                </integer-le>
              </globally>
            </globally>
          </next>
        </next>
      </all-paths>
    </formula>
  </property>
  <property>
    <id>PhaseVariation-PT-D10CS010-LTLCardinality-2</id>
    <description>Automatically generated</description>
    <formula>
      <all-paths>
        <integer-le>
          <tokens-count>
            <place>cell___5_3__B_</place>
          </tokens-count>
          <tokens-count>
            <place>pool__4_9_</place>
          </tokens-count>
        </integer-le>
      </all-paths>
    </formula>
  </property>
  <property>
    <id>PhaseVariation-PT-D10CS010-LTLCardinality-3</id>
    <description>Automatically generated</description>
    <formula>
      <all-paths>
        <globally>
          <integer-le>
            <tokens-count>
              <place>pool__3_3_</place>
            </tokens-count>
            <tokens-count>
              <place>cell___3_3__B_</place>
            </tokens-count>
          </integer-le>
        </globally>
      </all-paths>
    </formula>
  </property>
  <property>
    <id>PhaseVariation-PT-D10CS010-LTLCardinality-4</id>
    <description>Automatically generated</description>
    <formula>
      <all-paths>
        <finally>
          <until>
            <before>
              <finally>
                <integer-le>
                  <tokens-count>
                    <place>cell___10_10__A_</place>
                  </tokens-count>
                  <tokens-count>
                    <place>cell___10_2__B_</place>
                  </tokens-count>
                </integer-le>
              </finally>
            </before>
            <reach>
              <integer-le>
                <integer-constant>1</integer-constant>
                <tokens-count>
                  <place>cell___9_5__A_</place>
                </tokens-count>
              </integer-le>
            </reach>
          </until>
        </finally>
      </all-paths>
    </formula>
  </property>
  <property>
    <id>PhaseVariation-PT-D10CS010-LTLCardinality-5</id>
    <description>Automatically generated</description>
    <formula>
      <all-paths>
        <next>
          <finally>
            <next>
              <integer-le>
                <integer-constant>3</integer-constant>
                <tokens-count>
                  <place>cell___2_1__A_</place>
                </tokens-count>
              </integer-le>
            </next>
          </finally>
        </next>
      </all-paths>
    </formula>
  </property>
  <property>
    <id>PhaseVariation-PT-D10CS010-LTLCardinality-6</id>
    <description>Automatically generated</description>
    <formula>
      <all-paths>
        <finally>
          <integer-le>
            <integer-constant>3</integer-constant>
            <tokens-count>
              <place>cell___7_6__B_</place>
            </tokens-count>
          </integer-le>
        </finally>
      </all-paths>
    </formula>
  </property>
  <property>
    <id>PhaseVariation-PT-D10CS010-LTLCardinality-7</id>
    <description>Automatically generated</description>
    <formula>
      <all-paths>
        <next>
          <next>
            <until>
              <before>
                <integer-le>
                  <integer-constant>2</integer-constant>
                  <tokens-count>
                    <place>pool__6_4_</place>
                  </tokens-count>
                </integer-le>
              </before>
              <reach>
                <integer-le>
                  <tokens-count>
                    <place>pool__9_9_</place>
                  </tokens-count>
                  <tokens-count>
                    <place>pool__1_6_</place>
                  </tokens-count>
                </integer-le>
              </reach>
            </until>
          </next>
        </next>
      </all-paths>
    </formula>
  </property>
  <property>
    <id>PhaseVariation-PT-D10CS010-LTLCardinality-8</id>
    <description>Automatically generated</description>
    <formula>
      <all-paths>
        <next>
          <globally>
            <finally>
              <finally>
                <integer-le>
                  <tokens-count>
                    <place>cell___9_7__A_</place>
                  </tokens-count>
                  <tokens-count>
                    <place>pool__2_10_</place>
                  </tokens-count>
                </integer-le>
              </finally>
            </finally>
          </globally>
        </next>
      </all-paths>
    </formula>
  </property>
  <property>
    <id>PhaseVariation-PT-D10CS010-LTLCardinality-9</id>
    <description>Automatically generated</description>
    <formula>
      <all-paths>
        <next>
          <globally>
            <finally>
              <globally>
                <integer-le>
                  <tokens-count>
                    <place>cell___5_6__B_</place>
                  </tokens-count>
                  <tokens-count>
                    <place>cell___5_6__A_</place>
                  </tokens-count>
                </integer-le>
              </globally>
            </finally>
          </globally>
        </next>
      </all-paths>
    </formula>
  </property>
  <property>
    <id>PhaseVariation-PT-D10CS010-LTLCardinality-10</id>
    <description>Automatically generated</description>
    <formula>
      <all-paths>
        <finally>
          <next>
            <integer-le>
              <tokens-count>
                <place>cell___7_3__B_</place>
              </tokens-count>
              <tokens-count>
                <place>pool__5_1_</place>
              </tokens-count>
            </integer-le>
          </next>
        </finally>
      </all-paths>
    </formula>
  </property>
  <property>
    <id>PhaseVariation-PT-D10CS010-LTLCardinality-11</id>
    <description>Automatically generated</description>
    <formula>
      <all-paths>
        <until>
          <before>
            <integer-le>
              <tokens-count>
                <place>cell___3_9__B_</place>
              </tokens-count>
              <tokens-count>
                <place>pool__8_3_</place>
              </tokens-count>
            </integer-le>
          </before>
          <reach>
            <next>
              <globally>
                <integer-le>
                  <integer-constant>1</integer-constant>
                  <tokens-count>
                    <place>pool__10_1_</place>
                  </tokens-count>
                </integer-le>
              </globally>
            </next>
          </reach>
        </until>
      </all-paths>
    </formula>
  </property>
  <property>
    <id>PhaseVariation-PT-D10CS010-LTLCardinality-12</id>
    <description>Automatically generated</description>
    <formula>
      <all-paths>
        <until>
          <before>
            <until>
              <before>
                <integer-le>
                  <integer-constant>2</integer-constant>
                  <tokens-count>
                    <place>pool__6_6_</place>
                  </tokens-count>
                </integer-le>
              </before>
              <reach>
                <integer-le>
                  <tokens-count>
                    <place>cell___1_9__A_</place>
                  </tokens-count>
                  <tokens-count>
                    <place>cell___9_6__A_</place>
                  </tokens-count>
                </integer-le>
              </reach>
            </until>
          </before>
          <reach>
            <until>
              <before>
                <integer-le>
                  <tokens-count>
                    <place>cell___1_9__A_</place>
                  </tokens-count>
                  <tokens-count>
                    <place>cell___4_2__B_</place>
                  </tokens-count>
                </integer-le>
              </before>
              <reach>
                <integer-le>
                  <integer-constant>3</integer-constant>
                  <tokens-count>
                    <place>cell___4_10__B_</place>
                  </tokens-count>
                </integer-le>
              </reach>
            </until>
          </reach>
        </until>
      </all-paths>
    </formula>
  </property>
  <property>
    <id>PhaseVariation-PT-D10CS010-LTLCardinality-13</id>
    <description>Automatically generated</description>
    <formula>
      <all-paths>
        <integer-le>
          <tokens-count>
            <place>cell___6_8__B_</place>
          </tokens-count>
          <tokens-count>
            <place>cell___5_3__A_</place>
          </tokens-count>
        </integer-le>
      </all-paths>
    </formula>
  </property>
  <property>
    <id>PhaseVariation-PT-D10CS010-LTLCardinality-14</id>
    <description>Automatically generated</description>
    <formula>
      <all-paths>
        <finally>
          <next>
            <finally>
              <globally>
                <integer-le>
                  <integer-constant>1</integer-constant>
                  <tokens-count>
                    <place>cell___5_3__A_</place>
                  </tokens-count>
                </integer-le>
              </globally>
            </finally>
          </next>
        </finally>
      </all-paths>
    </formula>
  </property>
  <property>
    <id>PhaseVariation-PT-D10CS010-LTLCardinality-15</id>
    <description>Automatically generated</description>
    <formula>
      <all-paths>
        <next>
          <globally>
            <next>
              <finally>
                <integer-le>
                  <tokens-count>
                    <place>cell___3_2__B_</place>
                  </tokens-count>
                  <tokens-count>
                    <place>cell___6_5__A_</place>
                  </tokens-count>
                </integer-le>
              </finally>
            </next>
          </globally>
        </next>
      </all-paths>
    </formula>
  </property>
</property-set>
