<?xml version="1.0"?>
<property-set xmlns="http://mcc.lip6.fr/">
  <property>
    <id>CircularTrains-PT-192-LTLFireability-0</id>
    <description>Automatically generated</description>
    <formula>
      <all-paths>
        <globally>
          <next>
            <next>
              <next>
                <globally>
                  <is-fireable>
                    <transition>t164_to_165</transition>
                  </is-fireable>
                </globally>
              </next>
            </next>
          </next>
        </globally>
      </all-paths>
    </formula>
  </property>
  <property>
    <id>CircularTrains-PT-192-LTLFireability-1</id>
    <description>Automatically generated</description>
    <formula>
      <all-paths>
        <next>
          <globally>
            <next>
              <globally>
                <finally>
                  <is-fireable>
                    <transition>t48_to_49</transition>
                  </is-fireable>
                </finally>
              </globally>
            </next>
          </globally>
        </next>
      </all-paths>
    </formula>
  </property>
  <property>
    <id>CircularTrains-PT-192-LTLFireability-2</id>
    <description>Automatically generated</description>
    <formula>
      <all-paths>
        <is-fireable>
          <transition>t134_to_135</transition>
        </is-fireable>
      </all-paths>
    </formula>
  </property>
  <property>
    <id>CircularTrains-PT-192-LTLFireability-3</id>
    <description>Automatically generated</description>
    <formula>
      <all-paths>
        <is-fireable>
          <transition>t53_to_54</transition>
        </is-fireable>
      </all-paths>
    </formula>
  </property>
  <property>
    <id>CircularTrains-PT-192-LTLFireability-4</id>
    <description>Automatically generated</description>
    <formula>
      <all-paths>
        <next>
          <finally>
            <finally>
              <finally>
                <globally>
                  <is-fireable>
                    <transition>t149_to_150</transition>
                  </is-fireable>
                </globally>
              </finally>
            </finally>
          </finally>
        </next>
      </all-paths>
    </formula>
  </property>
  <property>
    <id>CircularTrains-PT-192-LTLFireability-5</id>
    <description>Automatically generated</description>
    <formula>
      <all-paths>
        <until>
          <before>
            <globally>
              <is-fireable>
                <transition>t149_to_150</transition>
              </is-fireable>
            </globally>
          </before>
          <reach>
            <until>
              <before>
                <next>
                  <is-fireable>
                    <transition>t172_to_173</transition>
                  </is-fireable>
                </next>
              </before>
              <reach>
                <globally>
                  <is-fireable>
                    <transition>t120_to_121</transition>
                  </is-fireable>
                </globally>
              </reach>
            </until>
          </reach>
        </until>
      </all-paths>
    </formula>
  </property>
  <property>
    <id>CircularTrains-PT-192-LTLFireability-6</id>
    <description>Automatically generated</description>
    <formula>
      <all-paths>
        <finally>
          <next>
            <is-fireable>
              <transition>t87_to_88</transition>
            </is-fireable>
          </next>
        </finally>
      </all-paths>
    </formula>
  </property>
  <property>
    <id>CircularTrains-PT-192-LTLFireability-7</id>
    <description>Automatically generated</description>
    <formula>
      <all-paths>
        <finally>
          <finally>
            <next>
              <next>
                <globally>
                  <is-fireable>
                    <transition>t128_to_129</transition>
                  </is-fireable>
                </globally>
              </next>
            </next>
          </finally>
        </finally>
      </all-paths>
    </formula>
  </property>
  <property>
    <id>CircularTrains-PT-192-LTLFireability-8</id>
    <description>Automatically generated</description>
    <formula>
      <all-paths>
        <finally>
          <next>
            <globally>
              <finally>
                <globally>
                  <is-fireable>
                    <transition>t52_to_53</transition>
                  </is-fireable>
                </globally>
              </finally>
            </globally>
          </next>
        </finally>
      </all-paths>
    </formula>
  </property>
  <property>
    <id>CircularTrains-PT-192-LTLFireability-9</id>
    <description>Automatically generated</description>
    <formula>
      <all-paths>
        <is-fireable>
          <transition>t59_to_60</transition>
        </is-fireable>
      </all-paths>
    </formula>
  </property>
  <property>
    <id>CircularTrains-PT-192-LTLFireability-10</id>
    <description>Automatically generated</description>
    <formula>
      <all-paths>
        <finally>
          <finally>
            <finally>
              <next>
                <globally>
                  <is-fireable>
                    <transition>t32_to_33</transition>
                  </is-fireable>
                </globally>
              </next>
            </finally>
          </finally>
        </finally>
      </all-paths>
    </formula>
  </property>
  <property>
    <id>CircularTrains-PT-192-LTLFireability-11</id>
    <description>Automatically generated</description>
    <formula>
      <all-paths>
        <is-fireable>
          <transition>t67_to_68</transition>
        </is-fireable>
      </all-paths>
    </formula>
  </property>
  <property>
    <id>CircularTrains-PT-192-LTLFireability-12</id>
    <description>Automatically generated</description>
    <formula>
      <all-paths>
        <is-fireable>
          <transition>t38_to_39</transition>
        </is-fireable>
      </all-paths>
    </formula>
  </property>
  <property>
    <id>CircularTrains-PT-192-LTLFireability-13</id>
    <description>Automatically generated</description>
    <formula>
      <all-paths>
        <next>
          <finally>
            <until>
              <before>
                <next>
                  <is-fireable>
                    <transition>t98_to_99</transition>
                  </is-fireable>
                </next>
              </before>
              <reach>
                <is-fireable>
                  <transition>t160_to_161</transition>
                </is-fireable>
              </reach>
            </until>
          </finally>
        </next>
      </all-paths>
    </formula>
  </property>
  <property>
    <id>CircularTrains-PT-192-LTLFireability-14</id>
    <description>Automatically generated</description>
    <formula>
      <all-paths>
        <next>
          <until>
            <before>
              <next>
                <is-fireable>
                  <transition>t161_to_162</transition>
                </is-fireable>
              </next>
            </before>
            <reach>
              <next>
                <next>
                  <is-fireable>
                    <transition>t55_to_56</transition>
                  </is-fireable>
                </next>
              </next>
            </reach>
          </until>
        </next>
      </all-paths>
    </formula>
  </property>
  <property>
    <id>CircularTrains-PT-192-LTLFireability-15</id>
    <description>Automatically generated</description>
    <formula>
      <all-paths>
        <globally>
          <finally>
            <finally>
              <until>
                <before>
                  <is-fireable>
                    <transition>t34_to_35</transition>
                  </is-fireable>
                </before>
                <reach>
                  <is-fireable>
                    <transition>t75_to_76</transition>
                  </is-fireable>
                </reach>
              </until>
            </finally>
          </finally>
        </globally>
      </all-paths>
    </formula>
  </property>
</property-set>
